{
  "$schema" : "https://json-schema.axonivy.com/14.0-dev/project/data-class.json",
  "simpleName" : "QuatumViewData",
  "namespace" : "com.axonivy.ups.connector",
  "fields" : [ {
    "name" : "version",
    "modifiers" : [ ]
  }, {
    "name" : "quantumViewRequest",
    "type" : "com.ups.wwwcie.api.client.QuantumViewRequest",
    "modifiers" : [ ]
  }, {
    "name" : "quantumViewResponse",
    "type" : "com.ups.wwwcie.api.client.QuantumViewResponse",
    "modifiers" : [ ]
  }, {
    "name" : "error",
    "type" : "ch.ivyteam.ivy.bpm.error.BpmError",
    "modifiers" : [ ]
  } ]
}